<?xml version="1.0" encoding="UTF-8"?>
<feature
      id="com.netifera.platform.core.feature"
      label="Netifera Core Feature"
      version="1.0.0">

   <description url="http://www.example.com/description">
      [Enter Feature Description here.]
   </description>

   <copyright url="http://www.example.com/copyright">
      [Enter Copyright Description here.]
   </copyright>

   <license url="http://www.example.com/license">
      [Enter License Description here.]
   </license>

   <requires>
      <import feature="org.eclipse.equinox" version="3.4.0" match="greaterOrEqual"/>
   </requires>

   <plugin
         id="com.netifera.platform.api"
         download-size="0"
         install-size="0"
         version="0.0.0"
         unpack="false"/>

   <plugin
         id="com.netifera.platform.kernel"
         download-size="0"
         install-size="0"
         version="0.0.0"
         unpack="false"/>

   <plugin
         id="com.netifera.platform.model"
         download-size="0"
         install-size="0"
         version="0.0.0"
         unpack="false"/>

   <plugin
         id="com.netifera.platform.tasks"
         download-size="0"
         install-size="0"
         version="0.0.0"
         unpack="false"/>

   <plugin
         id="com.netifera.platform.tools"
         download-size="0"
         install-size="0"
         version="0.0.0"
         unpack="false"/>

   <plugin
         id="com.netifera.platform.dispatcher"
         download-size="0"
         install-size="0"
         version="0.0.0"
         unpack="false"/>

   <plugin
         id="org.eclipse.equinox.ds"
         download-size="0"
         install-size="0"
         version="0.0.0"
         unpack="false"/>

   <plugin
         id="org.eclipse.equinox.log"
         download-size="0"
         install-size="0"
         version="0.0.0"
         unpack="false"/>

   <plugin
         id="org.eclipse.equinox.util"
         download-size="0"
         install-size="0"
         version="0.0.0"
         unpack="false"/>

   <plugin
         id="org.eclipse.osgi"
         download-size="0"
         install-size="0"
         version="0.0.0"
         unpack="false"/>

   <plugin
         id="org.eclipse.osgi.services"
         download-size="0"
         install-size="0"
         version="0.0.0"
         unpack="false"/>

   <plugin
         id="org.eclipse.equinox.common"
         download-size="0"
         install-size="0"
         version="0.0.0"
         unpack="false"/>

   <plugin
         id="com.netifera.platform.system"
         download-size="0"
         install-size="0"
         version="0.0.0"
         unpack="false"/>

   <plugin
         id="com.netifera.platform.system.linux"
         os="linux"
         download-size="0"
         install-size="0"
         version="0.0.0"
         fragment="true"
         unpack="false"/>

   <plugin
         id="com.netifera.platform.system.osx"
         os="macosx"
         download-size="0"
         install-size="0"
         version="0.0.0"
         fragment="true"
         unpack="false"/>

   <plugin
         id="com.netifera.platform.log"
         download-size="0"
         install-size="0"
         version="0.0.0"
         unpack="false"/>

   <plugin
         id="com.netifera.platform.channel.tcplisten"
         download-size="0"
         install-size="0"
         version="0.0.0"
         unpack="false"/>

   <plugin
         id="com.netifera.platform.probe"
         download-size="0"
         install-size="0"
         version="0.0.0"
         unpack="false"/>

   <plugin
         id="com.netifera.platform.util"
         download-size="0"
         install-size="0"
         version="0.0.0"
         unpack="false"/>

   <plugin
         id="com.netifera.platform.channel.tcpconnect"
         download-size="0"
         install-size="0"
         version="0.0.0"
         unpack="false"/>

</feature>
